slitherlib/__init__.py
slitherlib/config.py
slitherlib/slither.py
slitherlib/proxy/__init__.py
slitherlib/proxy/retriever.py
slitherlib/proxy/sources.py
slitherlib/user_agent/__init__.py
slitherlib/user_agent/ua.py
slitherlib-0.1.4.dist-info/LICENSE
slitherlib-0.1.4.dist-info/METADATA
slitherlib-0.1.4.dist-info/WHEEL
slitherlib-0.1.4.dist-info/top_level.txt
slitherlib-0.1.4.dist-info/RECORD
